hyprtiler/__init__.py
hyprtiler/click.py
hyprtiler/config.py
hyprtiler/constants.py
hyprtiler/kernel.py
hyprtiler-0.2.2.dist-info/METADATA
hyprtiler-0.2.2.dist-info/WHEEL
hyprtiler-0.2.2.dist-info/entry_points.txt
hyprtiler-0.2.2.dist-info/licenses/LICENSE
hyprtiler-0.2.2.dist-info/RECORD
