Metadata-Version: 2.4
Name: hyprtiler
Version: 0.2.2
Summary: A utility tool for managing windows in the Hyprland compositor environment.
Project-URL: homepage, https://github.com/antrax2024/hyprtiler
Project-URL: Repository, https://github.com/antrax2024/hyprtiler
Author-email: Antrax <fredcox@gmail.com>
License: MIT
License-File: LICENSE
Requires-Python: >=3.13
Requires-Dist: click>=8.1.8
Requires-Dist: hyprpy>=0.2.0
Requires-Dist: rich>=14.0.0
